README.md
setup.py
recordcapture/__init__.py
recordcapture/recordcapture.py
recordcapture.egg-info/PKG-INFO
recordcapture.egg-info/SOURCES.txt
recordcapture.egg-info/dependency_links.txt
recordcapture.egg-info/requires.txt
recordcapture.egg-info/top_level.txt