Metadata-Version: 2.1
Name: recordcapture
Version: 0.0.3
Summary: recordcapture is a library based on Desktop Duplication API, pillow, and pyaudio which provide multiple methods for capturing and recording Screen and Microphone.
Home-page: https://github.com/Sandeeppushp/recordcapture
Author: Sandeep Pushp
Author-email: sandeepkumarpushp@gmail.com
License: MIT
Platform: UNKNOWN
Classifier: License :: OSI Approved :: MIT License
Classifier: Programming Language :: Python :: 3
Classifier: Programming Language :: Python :: 3.9
Requires-Python: >=3.8
